CHANGES.md
MANIFEST.in
README.md
setup.py
django_terra_settings.egg-info/PKG-INFO
django_terra_settings.egg-info/SOURCES.txt
django_terra_settings.egg-info/dependency_links.txt
django_terra_settings.egg-info/requires.txt
django_terra_settings.egg-info/top_level.txt
terra_settings/VERSION.md
terra_settings/__init__.py
terra_settings/apps.py
terra_settings/mixins.py
terra_settings/models.py
terra_settings/pagination.py
terra_settings/settings.py
terra_settings/urls.py
terra_settings/views.py
terra_settings/base_layers/__init__.py
terra_settings/base_layers/serializers.py
terra_settings/base_layers/views.py
terra_settings/helpers/__init__.py
terra_settings/helpers/responses.py
terra_settings/locale/en/LC_MESSAGES/django.mo
terra_settings/locale/fr/LC_MESSAGES/django.mo
terra_settings/management/__init__.py
terra_settings/management/commands/__init__.py
terra_settings/management/commands/populatedata.py
terra_settings/templatetags/__init__.py
terra_settings/templatetags/settings_tags.py
terra_settings/tests/__init__.py
terra_settings/tests/test_commands.py
terra_settings/tests/test_helpers.py
terra_settings/tests/test_templatetags.py
terra_settings/tests/test_views.py
terra_settings/tests/test_app/__init__.py
terra_settings/tests/test_app/models.py
terra_settings/tests/test_app/serializers.py
terra_settings/tests/test_app/migrations/0001_initial.py
terra_settings/tests/test_app/migrations/__init__.py
terra_settings/tests/test_base_layers/__init__.py
terra_settings/tests/test_base_layers/test_base_layer_tiles.py
terra_settings/tests/test_base_layers/test_views.py